<?xml version="1.0" encoding="UTF-8"?>
<class xmlns:xs="https//www.w3.org/2001/XMLSchema" xs:noNamespaceSchemaLocation="studentIDA58U.xsd">
    <student id="1">
        <vezeteknev>Tóth</vezeteknev>
        <keresztnev>Milán</keresztnev>
        <becenev>Miló</becenev>
        <kor>22</kor>
        <osztondij>60000</osztondij>
    </student>
    <student id="2">
        <vezeteknev>Szabó</vezeteknev>
        <keresztnev>Kristóf</keresztnev>
        <becenev>Krinya</becenev>
        <kor>26</kor>
        <osztondij>52000</osztondij>
    </student>
    <student id="3">
        <vezeteknev>Lakatos</vezeteknev>
        <keresztnev>Béla</keresztnev>
        <becenev>Béci</becenev>
        <kor>35</kor>
        <osztondij>45000</osztondij>
    </student>
</class>